randf/__init__.py
randf/funcs.py
randf-0.1.0.dist-info/LICENCE
randf-0.1.0.dist-info/METADATA
randf-0.1.0.dist-info/WHEEL
randf-0.1.0.dist-info/top_level.txt
randf-0.1.0.dist-info/RECORD
