Metadata-Version: 2.1
Name: randf
Version: 0.1.0
Summary: A simple package for random DataFrame generation
Home-page: https://gitlab.com/manoelpqueiroz/randf
Author: Manoel Pereira de Queiroz
Author-email: git@manoelpqueiroz.anonaddy.com
License: MIT
Platform: UNKNOWN
Classifier: Development Status :: 1 - Planning
Classifier: License :: OSI Approved :: MIT License
Classifier: Natural Language :: English
Classifier: Programming Language :: Python
Classifier: Programming Language :: Python :: 3
Classifier: Programming Language :: Python :: 3.9
Classifier: Topic :: Software Development :: Libraries :: Python Modules
Requires-Dist: numpy
Requires-Dist: pandas
Requires-Dist: python-dateutil
Requires-Dist: pytz
Requires-Dist: six
